capsolai/__init__.py
capsolai/solver.py
capsolai-0.2.0.dist-info/licenses/LICENSE
capsolai-0.2.0.dist-info/METADATA
capsolai-0.2.0.dist-info/WHEEL
capsolai-0.2.0.dist-info/top_level.txt
capsolai-0.2.0.dist-info/RECORD
