Metadata-Version: 2.4
Name: capsolai
Version: 0.2.0
Summary: API wrapper for captchasolver.ai
Home-page: https://github.com/trailios/csai
Author: trailios
Author-email: Traili Cowyak <admin@bombing.lol>
License-Expression: Apache-2.0
Classifier: Programming Language :: Python :: 3
Classifier: Operating System :: OS Independent
Classifier: Development Status :: 3 - Alpha
Classifier: Intended Audience :: Developers
Classifier: Topic :: Software Development :: Libraries :: Python Modules
Requires-Python: >=3.7
License-File: LICENSE
Dynamic: author
Dynamic: home-page
Dynamic: license-file
Dynamic: requires-python
